open_swarm-0.1.1748636455.dist-info/licenses/LICENSE
swarm/__init__.py
swarm/apps.py
swarm/auth.py
swarm/consumers.py
swarm/core.py
swarm/messages.py
swarm/models.py
swarm/serializers.py
swarm/settings.py
swarm/tool_executor.py
swarm/types.py
swarm/urls.py
swarm/util.py
swarm/wsgi.py
swarm/agent/__init__.py
swarm/agent/agent.py
swarm/extensions/__init__.py
swarm/extensions/blueprint/__init__.py
swarm/extensions/blueprint/agent_utils.py
swarm/extensions/blueprint/blueprint_base.py
swarm/extensions/blueprint/blueprint_discovery.py
swarm/extensions/blueprint/blueprint_utils.py
swarm/extensions/blueprint/common_utils.py
swarm/extensions/blueprint/django_utils.py
swarm/extensions/blueprint/interactive_mode.py
swarm/extensions/blueprint/output_utils.py
swarm/extensions/blueprint/spinner.py
swarm/extensions/blueprint/modes/rest_mode.py
swarm/extensions/cli/__init__.py
swarm/extensions/cli/blueprint_runner.py
swarm/extensions/cli/cli_args.py
swarm/extensions/cli/interactive_shell.py
swarm/extensions/cli/main.py
swarm/extensions/cli/selection.py
swarm/extensions/cli/utils.py
swarm/extensions/cli/commands/__init__.py
swarm/extensions/cli/commands/blueprint_management.py
swarm/extensions/cli/commands/config_management.py
swarm/extensions/cli/commands/edit_config.py
swarm/extensions/cli/commands/list_blueprints.py
swarm/extensions/cli/commands/validate_env.py
swarm/extensions/cli/commands/validate_envvars.py
swarm/extensions/cli/utils/discover_commands.py
swarm/extensions/cli/utils/env_setup.py
swarm/extensions/config/__init__.py
swarm/extensions/config/config_loader.py
swarm/extensions/config/config_manager.py
swarm/extensions/config/server_config.py
swarm/extensions/config/setup_wizard.py
swarm/extensions/config/utils/__init__.py
swarm/extensions/config/utils/logger.py
swarm/extensions/launchers/__init__.py
swarm/extensions/launchers/build_launchers.py
swarm/extensions/launchers/build_swarm_wrapper.py
swarm/extensions/launchers/swarm_api.py
swarm/extensions/launchers/swarm_cli.py
swarm/extensions/launchers/swarm_wrapper.py
open_swarm-0.1.1748636455.dist-info/METADATA
open_swarm-0.1.1748636455.dist-info/WHEEL
open_swarm-0.1.1748636455.dist-info/entry_points.txt
open_swarm-0.1.1748636455.dist-info/top_level.txt
open_swarm-0.1.1748636455.dist-info/RECORD
