Metadata-Version: 2.4
Name: open-swarm
Version: 0.1.1748636455
Summary: A tool for orchestrating Swarm using both CLI and API.
Author-email: Matthew Hand <matthewhandau@gmail.com>
Requires-Python: >=3.10
License-File: LICENSE
Requires-Dist: aiofiles>=24.1.0
Requires-Dist: aiohttp>=3.11.11
Requires-Dist: asyncio>=3.4.3
Requires-Dist: asynctest>=0.13.0
Requires-Dist: channels>=4.2.0
Requires-Dist: colorama>=0.4.6
Requires-Dist: django<5.0,>=4.2
Requires-Dist: django-allauth>=65.3.1
Requires-Dist: django-template-debug>=0.3.5
Requires-Dist: djangorestframework>=3.15.2
Requires-Dist: flask>=3.1.0
Requires-Dist: jmespath>=1.0.1
Requires-Dist: jsonschema-pydantic>=0.6
Requires-Dist: mcp>=1.2.0
Requires-Dist: openai>=1.58.1
Requires-Dist: python-dotenv>=1.0.1
Requires-Dist: redis>=5.2.1
Requires-Dist: requests>=2.32.3
Requires-Dist: whitenoise>=6.8.2
Requires-Dist: drf-spectacular>=0.23.0
Requires-Dist: pyinstaller>=6.12.0
Requires-Dist: tiktoken>=0.9.0
Requires-Dist: django-cors-headers>=4.7.0
Provides-Extra: dev
Requires-Dist: pytest>=8.3.4; extra == "dev"
Requires-Dist: pytest-asyncio>=0.25.1; extra == "dev"
Requires-Dist: pytest-cov>=6.0.0; extra == "dev"
Requires-Dist: pytest-django>=4.9.0; extra == "dev"
Requires-Dist: pytest-mock>=3.14.0; extra == "dev"
Requires-Dist: python-semantic-release>=9.20.0; extra == "dev"
Provides-Extra: experimental
Requires-Dist: nemoguardrails>=0.11.0; extra == "experimental"
Dynamic: license-file
